README.rst
setup.cfg
setup.py
rbc/__init__.py
rbc/__main__.py
rbc/_backport.py
rbc/compiler.py
rbc/dumpast.py
rbc/exception.py
rbc/libb.b
rbc/libb.c
rbc/parser.py
rbc/semantics.py
rbc.egg-info/PKG-INFO
rbc.egg-info/SOURCES.txt
rbc.egg-info/dependency_links.txt
rbc.egg-info/entry_points.txt
rbc.egg-info/requires.txt
rbc.egg-info/top_level.txt
rbc/codegen/__init__.py
rbc/codegen/astnode.py
rbc/codegen/context.py
rbc/codegen/expression.py
rbc/codegen/external.py
rbc/codegen/statement.py
test/test_comments.py
test/test_compiler.py
test/test_dumpast.py
test/test_expressions.py
test/test_goto.py
test/test_if.py
test/test_import.py
test/test_simple_progs.py
test/test_stdlib.py
test/test_switch.py
test/test_unaryop.py
test/test_vector.py
test/test_while.py