Metadata-Version: 1.1
Name: rbc
Version: 0.2.0
Summary: Example B compiler written with LLVM
Home-page: https://github.com/rjw57/rbc
Author: Rich Wareham
Author-email: rich.rbc@richwareham.com
License: MIT
Keywords: compiler B llvm example
Platform: UNKNOWN
Classifier: Development Status :: 4 - Beta
Classifier: Intended Audience :: Developers
Classifier: Topic :: Software Development :: Code Generators
Classifier: Topic :: Software Development :: Compilers
Classifier: License :: OSI Approved :: MIT License
Classifier: Environment :: Console
Classifier: Programming Language :: Python :: 2.7
Classifier: Programming Language :: Python :: 3
